[
    [
        "E:\\VisualStudioFolder\\TestSFDXVideoRef\\My3rdProject\\force-app",
        {
            "state": "n",
            "sourcePath": "E:\\VisualStudioFolder\\TestSFDXVideoRef\\My3rdProject\\force-app",
            "isDirectory": true,
            "isMetadataFile": false,
            "size": 0,
            "modifiedTime": 1554283152042,
            "changeTime": 1554283152042,
            "contentHash": "b28b7af69320201d1cf206ebf28373980add1451",
            "isWorkspace": false,
            "isArtifactRoot": true
        }
    ],
    [
        "E:\\VisualStudioFolder\\TestSFDXVideoRef\\My3rdProject\\force-app\\main",
        {
            "state": "n",
            "sourcePath": "E:\\VisualStudioFolder\\TestSFDXVideoRef\\My3rdProject\\force-app\\main",
            "isDirectory": true,
            "isMetadataFile": false,
            "size": 0,
            "modifiedTime": 1554283152043,
            "changeTime": 1554283152043,
            "contentHash": "7505d64a54e061b7acd54ccd58b49dc43500b635",
            "isWorkspace": false,
            "isArtifactRoot": false
        }
    ],
    [
        "E:\\VisualStudioFolder\\TestSFDXVideoRef\\My3rdProject\\force-app\\main\\default",
        {
            "state": "n",
            "sourcePath": "E:\\VisualStudioFolder\\TestSFDXVideoRef\\My3rdProject\\force-app\\main\\default",
            "isDirectory": true,
            "isMetadataFile": false,
            "size": 0,
            "modifiedTime": 1554283152045,
            "changeTime": 1554283152045,
            "contentHash": "7334b1e8716ee057f8863fce77d3933d5bd9d984",
            "isWorkspace": false,
            "isArtifactRoot": false
        }
    ],
    [
        "E:\\VisualStudioFolder\\TestSFDXVideoRef\\My3rdProject\\force-app\\main\\default\\aura",
        {
            "state": "n",
            "sourcePath": "E:\\VisualStudioFolder\\TestSFDXVideoRef\\My3rdProject\\force-app\\main\\default\\aura",
            "isDirectory": true,
            "isMetadataFile": false,
            "size": 0,
            "modifiedTime": 1554283152044,
            "changeTime": 1554283152044,
            "contentHash": "da39a3ee5e6b4b0d3255bfef95601890afd80709",
            "isWorkspace": false,
            "isArtifactRoot": false
        }
    ],
    [
        "E:\\VisualStudioFolder\\TestSFDXVideoRef\\My3rdProject\\force-app\\main\\default\\lwc",
        {
            "state": "n",
            "sourcePath": "E:\\VisualStudioFolder\\TestSFDXVideoRef\\My3rdProject\\force-app\\main\\default\\lwc",
            "isDirectory": true,
            "isMetadataFile": false,
            "size": 0,
            "modifiedTime": 1554283173212,
            "changeTime": 1554283173212,
            "contentHash": "a973ac1b5be0e216b2a2db1b82ae5ba97f4086f4",
            "isWorkspace": false,
            "isArtifactRoot": false
        }
    ],
    [
        "E:\\VisualStudioFolder\\TestSFDXVideoRef\\My3rdProject",
        {
            "state": "n",
            "sourcePath": "E:\\VisualStudioFolder\\TestSFDXVideoRef\\My3rdProject",
            "isDirectory": true,
            "isMetadataFile": false,
            "size": 0,
            "modifiedTime": 1554283162754,
            "changeTime": 1554283162754,
            "contentHash": "829e604d4e7d5aae25f04d899b0bc5eccc598817",
            "isWorkspace": true,
            "isArtifactRoot": false
        }
    ]
]